pygameapp/__init__.py
pygameapp/app.py
pygameapp/constants.py
pygameapp/intern.py
pygameapp/props.py
pygameapp/types.py
pygameapp-0.0.2.dist-info/LICENSE
pygameapp-0.0.2.dist-info/METADATA
pygameapp-0.0.2.dist-info/WHEEL
pygameapp-0.0.2.dist-info/top_level.txt
pygameapp-0.0.2.dist-info/RECORD
